tests/__init__.py
tests/test_filecmp.py
tests/test_proxy.py
webdriver_browser/__init__.py
webdriver_browser/chrome.py
webdriver_browser/download.py
webdriver_browser/edge.py
webdriver_browser/firefox.py
webdriver_browser/patch.py
webdriver_browser/rsync.py
webdriver_browser/session.py
webdriver_browser/utils.py
webdriver_browser-0.3.0.dist-info/LICENSE
webdriver_browser-0.3.0.dist-info/METADATA
webdriver_browser-0.3.0.dist-info/WHEEL
webdriver_browser-0.3.0.dist-info/top_level.txt
webdriver_browser-0.3.0.dist-info/RECORD
